opentelemetry/extension/exporter/otlp/proto/http/__init__.py
opentelemetry/extension/exporter/otlp/proto/http/py.typed
opentelemetry/extension/exporter/otlp/proto/http/version.py
opentelemetry/extension/exporter/otlp/proto/http/metric_exporter/__init__.py
opentelemetry/extension/exporter/otlp/proto/http/metric_exporter/environment_variables.py
sb_opentelemetry_extension_exporter_otlp_proto_http-1.12.2.dist-info/LICENSE
sb_opentelemetry_extension_exporter_otlp_proto_http-1.12.2.dist-info/METADATA
sb_opentelemetry_extension_exporter_otlp_proto_http-1.12.2.dist-info/WHEEL
sb_opentelemetry_extension_exporter_otlp_proto_http-1.12.2.dist-info/top_level.txt
sb_opentelemetry_extension_exporter_otlp_proto_http-1.12.2.dist-info/RECORD
