Metadata-Version: 2.1
Name: sb-opentelemetry-extension-exporter-otlp-proto-http
Version: 1.12.2
Summary: OpenTelemetry Metrics over HTTP Exporter
Home-page: https://github.com/SibrosTech/otel-http/tree/master/python/exporter/opentelemetry-exporter-otlp-proto-http
Author: Rangel Reale
Author-email: Rangel Reale <rangelreale@gmail.com>
License: Apache License
Project-URL: Homepage, https://github.com/SibrosTech/otel-http
Project-URL: Bug Tracker, https://github.com/SibrosTech/otel-http/issues
Platform: any
Classifier: Programming Language :: Python :: 3
Classifier: License :: OSI Approved :: Apache Software License
Classifier: Operating System :: OS Independent
Requires-Python: >=3.6
License-File: LICENSE
Requires-Dist: requests (~=2.7)
Requires-Dist: opentelemetry-api (~=1.3)
Requires-Dist: opentelemetry-sdk (~=1.11)
Requires-Dist: opentelemetry-proto (==1.12.0)
Requires-Dist: opentelemetry-exporter-otlp-proto-http (~=1.11)
Requires-Dist: backoff (<2.0.0,>=1.10.0) ; python_version < "3.7"
Requires-Dist: backoff (<3.0.0,>=1.10.0) ; python_version >= "3.7"
Provides-Extra: test
